unicode_write/__init__.py
unicode_write/client.py
unicode_write/driver.py
unicode_write/serve.py
unicode_write/utils.py
unicode_write/data/__init__.py
unicode_write/data/emoji.json
unicode_write-0.2.0.dist-info/LICENSE.txt
unicode_write-0.2.0.dist-info/METADATA
unicode_write-0.2.0.dist-info/WHEEL
unicode_write-0.2.0.dist-info/entry_points.txt
unicode_write-0.2.0.dist-info/top_level.txt
unicode_write-0.2.0.dist-info/RECORD
